mjnf/__init__.py
mjnf/calc.py
mjnf/io.py
mjnf/main.py
source/__init__.py
source/calc.py
source/io.py
mjnf-0.1.2.dist-info/METADATA
mjnf-0.1.2.dist-info/WHEEL
mjnf-0.1.2.dist-info/entry_points.txt
mjnf-0.1.2.dist-info/top_level.txt
mjnf-0.1.2.dist-info/RECORD
