Metadata-Version: 2.4
Name: mjnf
Version: 0.1.2
Summary: Решение части 1 и полностью 2 номер из кр Сучкова линал
Author: zombyburger567
Dynamic: author
Dynamic: summary
